HACKING
MANIFEST.in
Makefile
VERSION
setup.py
charms/__init__.py
charms.benchmark.egg-info/PKG-INFO
charms.benchmark.egg-info/SOURCES.txt
charms.benchmark.egg-info/dependency_links.txt
charms.benchmark.egg-info/entry_points.txt
charms.benchmark.egg-info/requires.txt
charms.benchmark.egg-info/top_level.txt
charms/benchmark/__init__.py
charms/benchmark/cli/__init__.py
charms/benchmark/cli/actions.py
charms/benchmark/cli/composite.py
charms/benchmark/cli/data.py
charms/benchmark/cli/finish.py
charms/benchmark/cli/meta.py
charms/benchmark/cli/raw.py
charms/benchmark/cli/start.py
tests/__init__.py
tests/helpers.py
tests/test_charms-benchmark.py
tests/test_cli.py