Metadata-Version: 1.0
Name: charms.benchmark
Version: 1.0.5
Summary: Library to aid in the creation of benchmark actions in Juju
Home-page: https://github.com/juju-solutions/charms.benchmark
Author: Adam Israel
Author-email: adam@adamisrael.com
License: UNKNOWN
Platform: UNKNOWN
